aws_services_utils-0.0.6.dist-info/licenses/LICENSE
aws_utils/__init__.py
aws_utils/cloudwatch/__init__.py
aws_utils/cloudwatch/log_utils.py
aws_utils/cloudwatch/py.typed
aws_utils/ses/__init__.py
aws_utils/ses/email_manager.py
aws_utils/ssm/__init__.py
aws_utils/ssm/parameters_manager.py
aws_utils/ssm/py.typed
aws_services_utils-0.0.6.dist-info/METADATA
aws_services_utils-0.0.6.dist-info/WHEEL
aws_services_utils-0.0.6.dist-info/top_level.txt
aws_services_utils-0.0.6.dist-info/RECORD
