Metadata-Version: 2.4
Name: aws_services_utils
Version: 0.0.6
Summary: A set of tools providing utils for interacting with AWS tools
Author-email: Luigi Moro <luigi.moro.1976@gmail.com>
Keywords: aws,cloudwatch,ses
Classifier: Programming Language :: Python :: 3
Requires-Python: >=3.10
License-File: LICENSE
Requires-Dist: boto3>=1.34.19
Requires-Dist: mypy_boto3_ssm>=1.34.0
Dynamic: license-file
